{"candlesticks": [{"end_period_ts": 1743596160, "open_interest": 13092, "price": {"close": 46, "close_dollars": "0.4600", "high": 46, "high_dollars": "0.4600", "low": 46, "low_dollars": "0.4600", "max": null, "mean": 46, "mean_dollars": "0.4600", "min": null, "open": 46, "open_dollars": "0.4600", "previous": 46, "previous_dollars": "0.4600"}, "volume": 50, "yes_ask": {"close": 46, "close_dollars": "0.4600", "high": 46, "high_dollars": "0.4600", "low": 46, "low_dollars": "0.4600", "open": 46, "open_dollars": "0.4600"}, "yes_bid": {"close": 45, "close_dollars": "0.4500", "high": 45, "high_dollars": "0.4500", "low": 43, "low_dollars": "0.4300", "open": 45, "open_dollars": "0.4500"}}, {"end_period_ts": 1743596400, "open_interest": 13092, "price": {"close": null, "high": null, "low": null, "max": null, "mean": null, "min": null, "open": null, "previous": 46, "previous_dollars": "0.4600"}, "volume": 0, "yes_ask": {"close": 47, "close_dollars": "0.4700", "high": 47, "high_dollars": "0.4700", "low": 46, "low_dollars": "0.4600", "open": 46, "open_dollars": "0.4600"}, "yes_bid": {"close": 45, "close_dollars": "0.4500", "high": 45, "high_dollars": "0.4500", "low": 45, "low_dollars": "0.4500", "open": 45, "open_dollars": "0.4500"}}, {"end_period_ts": 1743596580, "open_interest": 13092, "price": {"close": null, "high": null, "low": null, "max": null, "mean": null, "min": null, "open": null, "previous": 46, "previous_dollars": "0.4600"}, "volume": 0, "yes_ask": {"close": 47, "close_dollars": "0.4700", "high": 47, "high_dollars": "0.4700", "low": 47, "low_dollars": "0.4700", "open": 47, "open_dollars": "0.4700"}, "yes_bid": {"close": 45, "close_dollars": "0.4500", "high": 45, "high_dollars": "0.4500", "low": 43, "low_dollars": "0.4300", "open": 45, "open_dollars": "0.4500"}}, {"end_period_ts": 1743596700, "open_interest": 13092, "price": {"close": null, "high": null, "low": null, "max": null, "mean": null, "min": null, "open": null, "previous": 46, "previous_dollars": "0.4600"}, "volume": 0, "yes_ask": {"close": 47, "close_dollars": "0.4700", "high": 47, "high_dollars": "0.4700", "low": 47, "low_dollars": "0.4700", "open": 47, "open_dollars": "0.4700"}, "yes_bid": {"close": 45, "close_dollars": "0.4500", "high": 45, "high_dollars": "0.4500", "low": 43, "low_dollars": "0.4300", "open": 45, "open_dollars": "0.4500"}}, {"end_period_ts": 1743597000, "open_interest": 13092, "price": {"close": null, "high": null, "low": null, "max": null, "mean": null, "min": null, "open": null, "previous": 46, "previous_dollars": "0.4600"}, "volume": 0, "yes_ask": {"close": 47, "close_dollars": "0.4700", "high": 47, "high_dollars": "0.4700", "low": 47, "low_dollars": "0.4700", "open": 47, "open_dollars": "0.4700"}, "yes_bid": {"close": 46, "close_dollars": "0.4600", "high": 46, "high_dollars": "0.4600", "low": 45, "low_dollars": "0.4500", "open": 45, "open_dollars": "0.4500"}}, {"end_period_ts": 1743597480, "open_interest": 13092, "price": {"close": 46, "close_dollars": "0.4600", "high": 46, "high_dollars": "0.4600", "low": 46, "low_dollars": "0.4600", "max": null, "mean": 46, "mean_dollars": "0.4600", "min": null, "open": 46, "open_dollars": "0.4600", "previous": 46, "previous_dollars": "0.4600"}, "volume": 35, "yes_ask": {"close": 47, "close_dollars": "0.4700", "high": 47, "high_dollars": "0.4700", "low": 47, "low_dollars": "0.4700", "open": 47, "open_dollars": "0.4700"}, "yes_bid": {"close": 46, "close_dollars": "0.4600", "high": 46, "high_dollars": "0.4600", "low": 46, "low_dollars": "0.4600", "open": 46, "open_dollars": "0.4600"}}, {"end_period_ts": 1743597780, "open_interest": 13092, "price": {"close": 47, "close_dollars": "0.4700", "high": 47, "high_dollars": "0.4700", "low": 47, "low_dollars": "0.4700", "max": null, "mean": 47, "mean_dollars": "0.4700", "min": null, "open": 47, "open_dollars": "0.4700", "previous": 46, "previous_dollars": "0.4600"}, "volume": 8, "yes_ask": {"close": 47, "close_dollars": "0.4700", "high": 47, "high_dollars": "0.4700", "low": 47, "low_dollars": "0.4700", "open": 47, "open_dollars": "0.4700"}, "yes_bid": {"close": 46, "close_dollars": "0.4600", "high": 46, "high_dollars": "0.4600", "low": 46, "low_dollars": "0.4600", "open": 46, "open_dollars": "0.4600"}}, {"end_period_ts": 1743600660, "open_interest": 13143, "price": {"close": 47, "close_dollars": "0.4700", "high": 47, "high_dollars": "0.4700", "low": 47, "low_dollars": "0.4700", "max": null, "mean": 47, "mean_dollars": "0.4700", "min": null, "open": 47, "open_dollars": "0.4700", "previous": 47, "previous_dollars": "0.4700"}, "volume": 51, "yes_ask": {"close": 47, "close_dollars": "0.4700", "high": 47, "high_dollars": "0.4700", "low": 47, "low_dollars": "0.4700", "open": 47, "open_dollars": "0.4700"}, "yes_bid": {"close": 46, "close_dollars": "0.4600", "high": 46, "high_dollars": "0.4600", "low": 46, "low_dollars": "0.4600", "open": 46, "open_dollars": "0.4600"}}, {"end_period_ts": 1743601800, "open_interest": 13143, "price": {"close": 46, "close_dollars": "0.4600", "high": 46, "high_dollars": "0.4600", "low": 46, "low_dollars": "0.4600", "max": null, "mean": 46, "mean_dollars": "0.4600", "min": null, "open": 46, "open_dollars": "0.4600", "previous": 47, "previous_dollars": "0.4700"}, "volume": 44, "yes_ask": {"close": 47, "close_dollars": "0.4700", "high": 47, "high_dollars": "0.4700", "low": 47, "low_dollars": "0.4700", "open": 47, "open_dollars": "0.4700"}, "yes_bid": {"close": 46, "close_dollars": "0.4600", "high": 46, "high_dollars": "0.4600", "low": 46, "low_dollars": "0.4600", "open": 46, "open_dollars": "0.4600"}}, {"end_period_ts": 1743604320, "open_interest": 13348, "price": {"close": 47, "close_dollars": "0.4700", "high": 47, "high_dollars": "0.4700", "low": 47, "low_dollars": "0.4700", "max": null, "mean": 47, "mean_dollars": "0.4700", "min": null, "open": 47, "open_dollars": "0.4700", "previous": 46, "previous_dollars": "0.4600"}, "volume": 205, "yes_ask": {"close": 47, "close_dollars": "0.4700", "high": 47, "high_dollars": "0.4700", "low": 47, "low_dollars": "0.4700", "open": 47, "open_dollars": "0.4700"}, "yes_bid": {"close": 46, "close_dollars": "0.4600", "high": 46, "high_dollars": "0.4600", "low": 46, "low_dollars": "0.4600", "open": 46, "open_dollars": "0.4600"}}, {"end_period_ts": 1743604920, "open_interest": 13348, "price": {"close": 46, "close_dollars": "0.4600", "high": 46, "high_dollars": "0.4600", "low": 46, "low_dollars": "0.4600", "max": null, "mean": 46, "mean_dollars": "0.4600", "min": null, "open": 46, "open_dollars": "0.4600", "previous": 47, "previous_dollars": "0.4700"}, "volume": 1, "yes_ask": {"close": 47, "close_dollars": "0.4700", "high": 47, "high_dollars": "0.4700", "low": 47, "low_dollars": "0.4700", "open": 47, "open_dollars": "0.4700"}, "yes_bid": {"close": 46, "close_dollars": "0.4600", "high": 46, "high_dollars": "0.4600", "low": 46, "low_dollars": "0.4600", "open": 46, "open_dollars": "0.4600"}}, {"end_period_ts": 1743605220, "open_interest": 13348, "price": {"close": 47, "close_dollars": "0.4700", "high": 47, "high_dollars": "0.4700", "low": 47, "low_dollars": "0.4700", "max": null, "mean": 47, "mean_dollars": "0.4700", "min": null, "open": 47, "open_dollars": "0.4700", "previous": 46, "previous_dollars": "0.4600"}, "volume": 743, "yes_ask": {"close": 48, "close_dollars": "0.4800", "high": 48, "high_dollars": "0.4800", "low": 47, "low_dollars": "0.4700", "open": 47, "open_dollars": "0.4700"}, "yes_bid": {"close": 47, "close_dollars": "0.4700", "high": 47, "high_dollars": "0.4700", "low": 46, "low_dollars": "0.4600", "open": 46, "open_dollars": "0.4600"}}, {"end_period_ts": 1743605280, "open_interest": 13348, "price": {"close": null, "high": null, "low": null, "max": null, "mean": null, "min": null, "open": null, "previous": 47, "previous_dollars": "0.4700"}, "volume": 0, "yes_ask": {"close": 48, "close_dollars": "0.4800", "high": 49, "high_dollars": "0.4900", "low": 48, "low_dollars": "0.4800", "open": 48, "open_dollars": "0.4800"}, "yes_bid": {"close": 46, "close_dollars": "0.4600", "high": 47, "high_dollars": "0.4700", "low": 46, "low_dollars": "0.4600", "open": 47, "open_dollars": "0.4700"}}, {"end_period_ts": 1743606300, "open_interest": 13348, "price": {"close": 45, "close_dollars": "0.4500", "high": 46, "high_dollars": "0.4600", "low": 45, "low_dollars": "0.4500", "max": null, "mean": 45, "mean_dollars": "0.4574", "min": null, "open": 46, "open_dollars": "0.4600", "previous": 47, "previous_dollars": "0.4700"}, "volume": 88, "yes_ask": {"close": 48, "close_dollars": "0.4800", "high": 48, "high_dollars": "0.4800", "low": 48, "low_dollars": "0.4800", "open": 48, "open_dollars": "0.4800"}, "yes_bid": {"close": 45, "close_dollars": "0.4500", "high": 46, "high_dollars": "0.4600", "low": 45, "low_dollars": "0.4500", "open": 46, "open_dollars": "0.4600"}}, {"end_period_ts": 1743606420, "open_interest": 13348, "price": {"close": null, "high": null, "low": null, "max": null, "mean": null, "min": null, "open": null, "previous": 45, "previous_dollars": "0.4500"}, "volume": 0, "yes_ask": {"close": 48, "close_dollars": "0.4800", "high": 48, "high_dollars": "0.4800", "low": 48, "low_dollars": "0.4800", "open": 48, "open_dollars": "0.4800"}, "yes_bid": {"close": 46, "close_dollars": "0.4600", "high": 46, "high_dollars": "0.4600", "low": 45, "low_dollars": "0.4500", "open": 45, "open_dollars": "0.4500"}}, {"end_period_ts": 1743606480, "open_interest": 13348, "price": {"close": null, "high": null, "low": null, "max": null, "mean": null, "min": null, "open": null, "previous": 45, "previous_dollars": "0.4500"}, "volume": 0, "yes_ask": {"close": 48, "close_dollars": "0.4800", "high": 48, "high_dollars": "0.4800", "low": 48, "low_dollars": "0.4800", "open": 48, "open_dollars": "0.4800"}, "yes_bid": {"close": 47, "close_dollars": "0.4700", "high": 47, "high_dollars": "0.4700", "low": 46, "low_dollars": "0.4600", "open": 46, "open_dollars": "0.4600"}}, {"end_period_ts": 1743606720, "open_interest": 13348, "price": {"close": null, "high": null, "low": null, "max": null, "mean": null, "min": null, "open": null, "previous": 45, "previous_dollars": "0.4500"}, "volume": 0, "yes_ask": {"close": 48, "close_dollars": "0.4800", "high": 49, "high_dollars": "0.4900", "low": 48, "low_dollars": "0.4800", "open": 48, "open_dollars": "0.4800"}, "yes_bid": {"close": 47, "close_dollars": "0.4700", "high": 47, "high_dollars": "0.4700", "low": 47, "low_dollars": "0.4700", "open": 47, "open_dollars": "0.4700"}}, {"end_period_ts": 1743606780, "open_interest": 13398, "price": {"close": 48, "close_dollars": "0.4800", "high": 48, "high_dollars": "0.4800", "low": 45, "low_dollars": "0.4500", "max": null, "mean": 47, "mean_dollars": "0.4772", "min": null, "open": 47, "open_dollars": "0.4700", "previous": 45, "previous_dollars": "0.4500"}, "volume": 58, "yes_ask": {"close": 48, "close_dollars": "0.4800", "high": 48, "high_dollars": "0.4800", "low": 48, "low_dollars": "0.4800", "open": 48, "open_dollars": "0.4800"}, "yes_bid": {"close": 45, "close_dollars": "0.4500", "high": 47, "high_dollars": "0.4700", "low": 45, "low_dollars": "0.4500", "open": 47, "open_dollars": "0.4700"}}, {"end_period_ts": 1743609360, "open_interest": 13428, "price": {"close": 48, "close_dollars": "0.4800", "high": 48, "high_dollars": "0.4800", "low": 48, "low_dollars": "0.4800", "max": null, "mean": 48, "mean_dollars": "0.4800", "min": null, "open": 48, "open_dollars": "0.4800", "previous": 48, "previous_dollars": "0.4800"}, "volume": 30, "yes_ask": {"close": 48, "close_dollars": "0.4800", "high": 48, "high_dollars": "0.4800", "low": 48, "low_dollars": "0.4800", "open": 48, "open_dollars": "0.4800"}, "yes_bid": {"close": 45, "close_dollars": "0.4500", "high": 45, "high_dollars": "0.4500", "low": 45, "low_dollars": "0.4500", "open": 45, "open_dollars": "0.4500"}}, {"end_period_ts": 1743609540, "open_interest": 13428, "price": {"close": null, "high": null, "low": null, "max": null, "mean": null, "min": null, "open": null, "previous": 48, "previous_dollars": "0.4800"}, "volume": 0, "yes_ask": {"close": 48, "close_dollars": "0.4800", "high": 49, "high_dollars": "0.4900", "low": 48, "low_dollars": "0.4800", "open": 48, "open_dollars": "0.4800"}, "yes_bid": {"close": 45, "close_dollars": "0.4500", "high": 45, "high_dollars": "0.4500", "low": 45, "low_dollars": "0.4500", "open": 45, "open_dollars": "0.4500"}}, {"end_period_ts": 1743610140, "open_interest": 13524, "price": {"close": 48, "close_dollars": "0.4800", "high": 48, "high_dollars": "0.4800", "low": 48, "low_dollars": "0.4800", "max": null, "mean": 48, "mean_dollars": "0.4800", "min": null, "open": 48, "open_dollars": "0.4800", "previous": 48, "previous_dollars": "0.4800"}, "volume": 96, "yes_ask": {"close": 48, "close_dollars": "0.4800", "high": 48, "high_dollars": "0.4800", "low": 48, "low_dollars": "0.4800", "open": 48, "open_dollars": "0.4800"}, "yes_bid": {"close": 45, "close_dollars": "0.4500", "high": 45, "high_dollars": "0.4500", "low": 45, "low_dollars": "0.4500", "open": 45, "open_dollars": "0.4500"}}, {"end_period_ts": 1743610320, "open_interest": 13524, "price": {"close": null, "high": null, "low": null, "max": null, "mean": null, "min": null, "open": null, "previous": 48, "previous_dollars": "0.4800"}, "volume": 0, "yes_ask": {"close": 49, "close_dollars": "0.4900", "high": 49, "high_dollars": "0.4900", "low": 48, "low_dollars": "0.4800", "open": 48, "open_dollars": "0.4800"}, "yes_bid": {"close": 45, "close_dollars": "0.4500", "high": 45, "high_dollars": "0.4500", "low": 45, "low_dollars": "0.4500", "open": 45, "open_dollars": "0.4500"}}], "ticker": "KXPAYROLLS-25MAR-T150000"}